llama_index/storage/kvstore/gel/__init__.py
llama_index/storage/kvstore/gel/base.py
llama_index_storage_kvstore_gel-0.2.1.dist-info/METADATA
llama_index_storage_kvstore_gel-0.2.1.dist-info/WHEEL
llama_index_storage_kvstore_gel-0.2.1.dist-info/licenses/LICENSE
llama_index_storage_kvstore_gel-0.2.1.dist-info/RECORD
