Metadata-Version: 2.4
Name: llama-index-storage-kvstore-gel
Version: 0.2.1
Summary: llama-index kvstore gel integration
Author-email: Your Name <you@example.com>
License-Expression: MIT
License-File: LICENSE
Requires-Python: <4.0,>=3.9
Requires-Dist: gel>=3.0.1
Requires-Dist: jinja2>=3.1.4
Requires-Dist: llama-index-core<0.15,>=0.13.0
